LICENSE
MANIFEST.in
README.rst
setup.py
accounts/__init__.py
accounts/admin.py
accounts/apps.py
accounts/conf.py
accounts/models.py
accounts/permissions.py
accounts/serializers.py
accounts/signals.py
accounts/tests.py
accounts/urls.py
accounts/utils.py
accounts/views.py
accounts/migrations/__init__.py
docs/blank.txt
rest_accounts.egg-info/PKG-INFO
rest_accounts.egg-info/SOURCES.txt
rest_accounts.egg-info/dependency_links.txt
rest_accounts.egg-info/requires.txt
rest_accounts.egg-info/top_level.txt